README.rst
setup.py
bilibili_voice.egg-info/PKG-INFO
bilibili_voice.egg-info/SOURCES.txt
bilibili_voice.egg-info/dependency_links.txt
bilibili_voice.egg-info/entry_points.txt
bilibili_voice.egg-info/requires.txt
bilibili_voice.egg-info/top_level.txt
bilibilivoice/__init__.py
bilibilivoice/api.py
bilibilivoice/cache.py
bilibilivoice/const.py
bilibilivoice/logger.py
bilibilivoice/menu.py
bilibilivoice/mpv.py
bilibilivoice/player.py
bilibilivoice/scrollstring.py
bilibilivoice/singleton.py
bilibilivoice/storage.py
bilibilivoice/terminalsize.py
bilibilivoice/ui.py
bilibilivoice/utils.py