Metadata-Version: 1.0
Name: bilibili-voice
Version: 0.2.0.2
Summary: bilibili-voice is a native audio player for BiliBili video in command line mode
Home-page: https://github.com/gogoforit/bilibili-voice
Author: gogoforit
Author-email: 715157026@qq.com
License: MIT
Keywords: music,bilibili,cli,voice
Platform: Ubuntu
Platform: Mac OS
